Workbook
Name _________AFC1: [1]INV!$A$25:$D$28
Name _________AFC3: [1]INV!$F$25:$I$28
Name _________AFC5: [1]INV!$K$25:$N$28
Name _________BGC1: [1]INV!$A$5:$D$8
Name _________BGC3: [1]INV!$F$5:$I$8
Name _________BGC5: [1]INV!$K$5:$N$8
Name _________CAC1: [1]INV!$A$19:$D$22
Name _________CAC3: [1]INV!$F$19:$I$22
Name _________CAC5: [1]INV!$K$19:$N$22
Name _________key2: [2]INST!#REF!
Name _________key2: [2]INST!#REF!
Name _________PJ50: #REF!
Name _________PJ50: #REF!
Name _________SBC1: [1]INV!$A$12:$D$15
Name _________SBC3: [1]INV!$F$12:$I$15
Name _________SBC5: [1]INV!$K$12:$N$15
Name ________AFC1: [1]INV!$A$25:$D$28
Name ________AFC3: [1]INV!$F$25:$I$28
Name ________AFC5: [1]INV!$K$25:$N$28
Name ________BGC1: [1]INV!$A$5:$D$8
Name ________BGC3: [1]INV!$F$5:$I$8
Name ________BGC5: [1]INV!$K$5:$N$8
Name ________CAC1: [1]INV!$A$19:$D$22
Name ________CAC3: [1]INV!$F$19:$I$22
Name ________CAC5: [1]INV!$K$19:$N$22
Name ________key2: [3]INST!#REF!
Name ________key2: [3]INST!#REF!
Name ________key3: #REF!
Name ________key3: #REF!
Name ________MA2: #REF!
Name ________MA2: #REF!
Name ________PJ50: #REF!
Name ________PJ50: #REF!
Name ________SBC1: [1]INV!$A$12:$D$15
Name ________SBC3: [1]INV!$F$12:$I$15
Name ________SBC5: [1]INV!$K$12:$N$15
Name _______AFC1: [1]INV!$A$25:$D$28
Name _______AFC3: [1]INV!$F$25:$I$28
Name _______AFC5: [1]INV!$K$25:$N$28
Name _______BGC1: [1]INV!$A$5:$D$8
Name _______BGC3: [1]INV!$F$5:$I$8
Name _______BGC5: [1]INV!$K$5:$N$8
Name _______CAC1: [1]INV!$A$19:$D$22
Name _______CAC3: [1]INV!$F$19:$I$22
Name _______CAC5: [1]INV!$K$19:$N$22
Name _______MA2: #REF!
Name _______MA2: #REF!
Name _______PJ50: #REF!
Name _______PJ50: #REF!
Name _______SBC1: [1]INV!$A$12:$D$15
Name _______SBC3: [1]INV!$F$12:$I$15
Name _______SBC5: [1]INV!$K$12:$N$15
Name ______AFC1: [1]INV!$A$25:$D$28
Name ______AFC3: [1]INV!$F$25:$I$28
Name ______AFC5: [1]INV!$K$25:$N$28
Name ______BGC1: [1]INV!$A$5:$D$8
Name ______BGC3: [1]INV!$F$5:$I$8
Name ______BGC5: [1]INV!$K$5:$N$8
Name ______CAC1: [1]INV!$A$19:$D$22
Name ______CAC3: [1]INV!$F$19:$I$22

Sheet PRESUPUESTO
C4: Código | E4: Versión
C5: FORMULARIO 1
C6: PROPUESTA ECONÓMICA
C7: [La entidad puede utilizar este formulario de presentación de propuesta económica de forma detallada, sin perjuicio que la entidad pueda modificarlo o establecer la presentación de la oferta económica con un formulario distinto al indicado.] [Los proponentes emplearán el formulario establecido por la entidad para determinar su propuesta económica conforme al Formulario 1 - Presupuesto Oficial publicado por la Entidad]
C9: Cuando el proceso de contratación es estructurado por precios unitarios, la Entidad debe aplicar las notas 1, 2 y 3 del presente formato y las casillas de "Descripción", "Porcentaje" de la Administración, Utilidad y total A.I.U. resaltadas en color amarillo.
C11: Nº | D11: ÍTEM DE PAGO | E11: ESPECIFICACIONES | G11: DESCRIPCIÓN | H11: UND. | I11: CANTIDAD | J11: VALOR UNITARIO | K11: VALOR TOTAL
E12: GENERAL | F12: PARTICULAR
D13: 003 | G13: DESAGUES E INSTALACIONES SANITARIAS
D14: 003.014 | G14: SUMINISTRO, TRANSPORTE E INSTALACION PUNTO DESAGUE PVC 3" APARATOS SANITARIOS Y DESAGUES (INCLUYE CODO, YEE Y ACCESORIOS) | H14: UND. | I14: 1 | J14: 158003 | K14: =+ROUND(J14*I14,0) -> 158003
D15: 003.015 | G15: SUMINISTRO, TRANSPORTE E INSTALACION PUNTO DESAGUE PVC 3" APARATOS SANITARIOS Y DESAGUES (INCLUYE CODO, YEE Y ACCESORIOS) | H15: UND. | I15: 1 | J15: 206188 | K15: =+ROUND(J15*I15,0) -> 206188
C16: Subtotal | K16: =SUM(K14:K15) -> 364191
D17: 006 | G17: MAMPOSTERIA
D18: 006.019 | G18: SUMINISTRO, TRANSPORTE E INSTALACIÓN A TODO COSTO DE MURO EN SUPERBOARD 8 MM PINTADO Y TERMINADO (DOS CARAS). INCLUYE PERFILERÍA Y TODO LO NECESARIO PARA SU CORRECTA INSTALACIÓN | H18: M2 | I18: 135.19 | J18: 201149 | K18: =+ROUND(J18*I18,0) -> 27193333
C19: Subtotal | K19: =SUM(K18) -> 27193333
D20: 007 | G20: INSTALACIONES HIDRAULICAS
D21: 007.017 | G21: SUMINISTRO, TRANSPORTE E INSTALACION PUNTO AGUA FRIA 1/2" PVC -P ( INCLUYE ACCESORIOS DE INSTALACIÓN ) | H21: UND | I21: 1 | J21: 96040 | K21: =+ROUND(J21*I21,0) -> 96040
D22: 007.021 | G22: SUMINISTRO, TRANSPORTE E INSTALACION PUNTO AGUA CALIENTE 1/2" CPVC-P ( INCLUYE ACCESORIOS DE INSTALACIÓN ) | H22: UND | I22: 1 | J22: 182492 | K22: =+ROUND(J22*I22,0) -> 182492
C23: Subtotal | K23: =SUM(K21:K22) -> 278532
D24: 08B | G24: INSTALACIONES HIDRAULICAS
G25: INSTALACIONES ELECTRICAS
D26: 08B.844 | G26: SUMINISTRO E INSTALACIÓN BREAKER TOTALIZADOR 3X40A | H26: UND | I26: 3 | J26: 590278 | K26: =+ROUND(J26*I26,0) -> 1770834
D27: 08B.845 | G27: SUMINISTRO E INSTALACIÓN DE ACOMETIDA A TR EN CABLE DE COBRE HFFRLS 3#8(F)+1#8(N)+1#8(T), POR BANDEJA EXISTENTE | H27: ML | I27: 150 | J27: 77863 | K27: =+ROUND(J27*I27,0) -> 11679450
D28: 08B.846 | G28: SUMINISTRO E INSTALACIÓN TABLERO TRIFÁSICO DE 24 CTOS. CON ESPACIO PARA TOTALIZADOR (TN) | H28: UND | I28: 1 | J28: 938955 | K28: =+ROUND(J28*I28,0) -> 938955
D29: 08B.847 | G29: SUMINISTRO E INSTALACIÓN BREAKER ENCHUFABLE 1X20 A | H29: UND | I29: 64 | J29: 75923 | K29: =+ROUND(J29*I29,0) -> 4859072
D30: 08B.848 | G30: SUMINISTRO E INSTALACIÓN BREAKER ENCHUFABLE 2X20A | H30: UND | I30: 3 | J30: 160412 | K30: =+ROUND(J30*I30,0) -> 481236
D31: 08B.849 | G31: SUMINISTRO E INSTALACIÓN SALIDA ALUMBRADO CON TUBERÍA PVC SCH40 Y CABLE #12 HFFRLS | H31: UND | I31: 238 | J31: 177181 | K31: =+ROUND(J31*I31,0) -> 42169078
D32: 08B.850 | G32: SUMINISTRO E INSTALACIÓN SALIDA CON SENSOR DE MOVIMIENTO DE TECHO PARA ALUMBRADO CON TUBERÍA SCH40 Y CABLE #12 HFFRLS | H32: UND | I32: 5 | J32: 251167 | K32: =+ROUND(J32*I32,0) -> 1255835
D33: 08B.851 | G33: SUMINISTRO E INSTALACIÓN SALIDA INTERRUPTOR SENCILLO CON TUBERÍA PVC SCH40 Y CABLE #12 HFFRLS | H33: UND | I33: 26 | J33: 182809 | K33: =+ROUND(J33*I33,0) -> 4753034
D34: 08B.852 | G34: SUMINISTRO E INSTALACIÓN SALIDA INTERRUPTOR SENCILLO CON CABLE #12 LIBRE DE HALÓGENOS Y TUBERÍA PVC 1/2" | H34: UND | I34: 13 | J34: 205854 | K34: =+ROUND(J34*I34,0) -> 2676102
D35: 08B.853 | G35: SUMINISTRO E INSTALACIÓN SALIDA INTERRUPTOR DOBLE CON TUBERÍA PVC SCH40 Y CABLE #12 HFFRLS | H35: UND | I35: 7 | J35: 207797 | K35: =+ROUND(J35*I35,0) -> 1454579
D36: 08B.854 | G36: SUMINISTRO E INSTALACIÓN SALIDA INTERRUPTOR DOBLE CON CABLE #12 LIBRE DE HALÓGENOS Y TUBERÍA PVC 1/2" | H36: UND | I36: 3 | J36: 227671 | K36: =+ROUND(J36*I36,0) -> 683013
D37: 08B.855 | G37: SUMINISTRO E INSTALACIÓN SALIDA INTERRUPTOR TRIPLE CON TUBERÍA PVC SCH40 Y CABLE #12 HFFRLS | H37: UND | I37: 2 | J37: 234126 | K37: =+ROUND(J37*I37,0) -> 468252
... D61: 08B.880 | G61: SUMINISTRO E INSTALACIÓN TUBERÍA PVC SCH40 2" | H61: ML | I61: 59 | J61: 24598 | K61: =+ROUND(J61*I61,0) -> 1451282
G62: INSTALACIONES VOZ-DATOS
D63: 08B.881 | G63: SUMINISTRO E INSTALACIÓN CABLE UTP CAT. 6A 4P | H63: ML | I63: 9760 | J63: 11124 | K63: =+ROUND(J63*I63,0) -> 108570240
D64: 08B.882 | G64: SUMINISTRO E INSTALACIÓN TOMA RJ45 DOBLE CAT. 6A | H64: UND | I64: 156 | J64: 148727 | K64: =+ROUND(J64*I64,0) -> 23201412
D65: 08B.883 | G65: SUMINISTRO E INSTALACIÓN TOMA RJ45 SENCILLO CAT. 6A | H65: UND | I65: 10 | J65: 89217 | K65: =+ROUND(J65*I65,0) -> 892170
D66: 08B.884 | G66: SUMINISTRO E INSTALACIÓN HERRAJE ANGULADO 48 PTOS | H66: UND | I66: 6 | J66: 621577 | K66: =+ROUND(J66*I66,0) -> 3729462
D67: 08B.885 | G67: SUMINISTRO E INSTALACIÓN HERRAJE ANGULADO 24 PTOS | H67: UND | I67: 2 | J67: 621577 | K67: =+ROUND(J67*I67,0) -> 1243154
D68: 08B.886 | G68: SUMINISTRO E INSTALACIÓN JACK RJ45 CAT. 6A (EN RACK) | H68: UND | I68: 322 | J68: 61992 | K68: =+ROUND(J68*I68,0) -> 19961424
D69: 08B.887 | G69: SUMINISTRO E INSTALACIÓN PATCH CORD RJ45 30 CM CAT. 6A | H69: UND | I69: 322 | J69: 37729 | K69: =+ROUND(J69*I69,0) -> 12148738
D70: 08B.888 | G70: SUMINISTRO E INSTALACIÓN ORGANIZADOR HORIZONTAL 2RU | H70: UND | I70: 6 | J70: 507411 | K70: =+ROUND(J70*I70,0) -> 3044466
D71: 08B.889 | G71: CERTIFICACION SALIDA DATOS | H71: UND | I71: 322 | J71: 25821 | K71: =+ROUND(J71*I71,0) -> 8314362
C72: Subtotal | K72: =SUM(K25:K71) -> 378505507
D73: 009 | G73: REVOQUES- RESANES
D74: 009.001 | G74: SUMINISTRO,TRANSPORTE E INSTALACION REVOQUE LISO MUROS 1:3 INTERIOR ( INCLUYE FILOS Y DILATACIONES ) | H74: M2 | I74: 4.8 | J74: 49887 | K74: =+ROUND(J74*I74,0) -> 239458
C75: Subtotal | K75: =SUM(K74) -> 239458
D76: 011 | G76: CIELO RASOS
D77: 011.005 | G77: SUMINISTRO, TRANSPORTE E INSTALACION CIELO RASO SUSPENDIDO DRYWALL JUNTA PERDIDA DE 0-0,6M (PERFILERIA METÁLICA CL. 26. ESTRUCTURA CADA 40 CMS.) INCLUYE TRES (3) MANOS DE PINTURA | H77: M2 | I77: 530.3 | J77: 124162 | K77: =+ROUND(J77*I77,0) -> 65843109
C78: Subtotal | K78: =SUM(K77) -> 65843109
D79: 012 | G79: PISOS - ACABADOS
D80: 012.098 | G80: SUMINISTRO, TRANSPORTE E INSTALACION ENCHAPE PISO BAÑO Petra Tortora 60x60cm Tipo CORONA o SIMILAR. Color Café/Marrón. (Incluye mortero de nivelación, boquilla y pegante) | H80: M2 | I80: 4 | J80: 112200 | K80: =+ROUND(J80*I80,0) -> 448800
D81: 012.003 | G81: SUMINISTRO, TRANSPORTE E INSTALACION ALISTADO PISOS MORTERO 1:3 E= 0.04 MTS | H81: M2 | I81: 126.9 | J81: 54135 | K81: =+ROUND(J81*I81,0) -> 6869732
D82: 012.105 | G82: SUMINISTRO, TRANSPORTE E INSTALACIÓN A TODO COSTO DE MORTERO AUTONIVELANTE HASTA 5,00MM DE ESPESOR PARA PISOS VINILICOS | H82: M2 | I82: 634.5 | J82: 93368 | K82: =+ROUND(J82*I82,0) -> 59241996
D83: 012.006 | G83: SUMINISTRO, TRANSPORTE E INSTALACION CERAMICA PISO POMPEI TIPO ALFA O SIMILAR. COLOR CORAL O SHELL SEGÚN DISEÑO. INCLUYE MORTERO DE PEGA Y/O NIVELACIÓN | H83: M2 | I83: 5.03 | J83: 104427 | K83: =+ROUND(J83*I83,0) -> 525268
D84: 012.088 | G84: SUMINISTRO E INSTALACION PISO HOMOGENEO VINILICO EN ROLLO, 2 MM DE ESPESOR, ANCHO ROLLO 2MT, COLOR SEGÚN DISEÑO, ALTO TRAFICO INCLUYE PREPARACION DE SUPERFICIE CON MASTICO, SOLDADURA PARA JUNTAS, ADHESIVO/PEGANTE, PARA AREAS | H84: M2 | I84: 634.5 | J84: 292653 | K84: =+ROUND(J84*I84,0) -> 185688329
D85: 012.106 | G85: SUMINISTRO, TRANSPORTE E INSTALACION GUARDAESCOBA EN PVC RECUBIERTO | H85: ML | I85: 768.72 | J85: 43030 | K85: =+ROUND(J85*I85,0) -> 33078022
D86: 012.077 | G86: SUMINISTRO, TRANSPORTE E INSTALACION BALDOSA GRANO TRADICIONAL PAYANDE TERRAZO. TIPO ALFA O SIMILAR. FONDO BLANCO (INCLUYE DESTRONCADA, PULIDA, BRILLADA, MORTERO DE NIVELACIÓN Y DILATACIÓN EN PVC.) | H86: M2 | I86: 4.53 | J86: 271793 | K86: =+ROUND(J86*I86,0) -> 1231222
C87: Subtotal | K87: =SUM(K80:K86) -> 287083369
D88: 013 | G88: ENCHAPES Y ACCESORIOS
D89: 013.001 | G89: SUMINISTRO, TRANSPORTE E INSTALACION CERAMICA PARED POMPEI TIPO ALFA O SIMILAR. COLOR CORAL O SHELL SEGÚN DISEÑO (INCLUYE BOQUILLA COLOR Y WIN.) | H89: M2 | I89: 25.31 | J89: 117964 | K89: =+ROUND(J89*I89,0) -> 2985669
D90: 013.065 | G90: SUMINISTRO, TRANSPORTE E INSTALACION MESON EN QUARZTONE BLANCO POLAR 1,00X0,50M | H90: ML | I90: 3 | J90: 831943 | K90: =+ROUND(J90*I90,0) -> 2495829
C91: Subtotal | K91: =SUM(K89:K90) -> 5481498
D92: 014 | G92: VIDRIOS Y ESPEJOS
D93: 014.001 | G93: SUMINISTRO, TRANSPORTE E INSTALACION ESPEJO 4 MM. FLOTADO BISELADO Y SIN MARCO. (INCLUYE LOS ELEMENTOS DE FIJACIÓN AL MURO). | H93: M2 | I93: 1.02 | J93: 241340 | K93: =+ROUND(J93*I93,0) -> 246167
C94: Subtotal | K94: =SUM(K93) -> 246167
D95: 015 | G95: APARATOS SANITARIOS
D96: 015.004 | G96: SUMINISTRO, TRANSPORTE E INSTALACION SANITARIO MONTECARLO ELONGADO BLANCO CORONA O SIMILAR. (CONJUNTO SANITARIO QUE INCLUYE SANITARIO, TAPA, ACCESORIOS DE CONEXIÓN E INSTALACIÓN.) | H96: UND | I96: 2 | J96: 1211471 | K96: =+ROUND(J96*I96,0) -> 2422942
D97: 015.012 | G97: SUMINISTRO, TRANSPORTE E INSTALACION LAVAMANOS SOBREPONER LINEA STILO COLOR BLANCO TIPO CORONA REF. 072591001 O SIMILAR (INCLUYE CONJUNTO GRIFERIA DESAGÜE AUTOMATICO, SIFÓN BOTELLA, ACOPLE). | H97: UND | I97: 2 | J97: 794895 | K97: =+ROUND(J97*I97,0) -> 1589790
C98: Subtotal | K98: =SUM(K96:K97) -> 4012732
D99: 016 | G99: CARPINTERIA DE MADERA
D100: 016.007 | G100: SUMINISTRO, TRANSPORTE E INSTALACION PUERTA ENTAMBORADA EN MADEFONDO - TIPO PIZANO ARQUITECTÓNICA O SIMILAR. ANCHO: 0,51 A 0,75 M. ALTO: 1,80 A 2,40 M. HOJA LISA CON 4 RANURAS HORIZONTALES PINTADAS Y CON MARQUETE EN CANTO DECORATIVO. ACABADO: SEGÚN PINTA SELECCIONADA DE CARTA COLORES MADECOR. (INCLUYE BISAGRAS). | H100: UND | I100: 2 | J100: 473697 | K100: =+ROUND(J100*I100,0) -> 947394
D101: 016.008 | G101: SUMINISTRO, TRANSPORTE E INSTALACION PUERTA ENTAMBORADA EN MADEFONDO - TIPO PIZANO ARQUITECÓNICA O SIMILAR. ANCHO: 0,76 A 1,10 M. ALTO: 1,80 A 2,40 M. HOJA LISA CON 4 RANURAS HORIZONTALES PINTADAS Y CON MARQUETE EN CANTO DECORATIVO. ACABADO: SEGÚN PINTA SELECCIONADA DE CARTA COLORES MADECOR. (INCLUYE BISAGRAS). | H101: UND | I101: 2 | J101: 549521 | K101: =+ROUND(J101*I101,0) -> 1099042
D102: 016.010 | G102: SUMINISTRO, TRANSPORTE E INSTALACION MARCO EN TABLEX ENCHAPADO OKUME - KIT DE MARKO CLASSICO TIPO PIZANO O SIMILAR. (2 LARGUEROS DE 2,40 M Y UN CABEZAL DE 1,20 M.) ANCHO MURO: 10 A 18 CM ANCHO PUERTA: 0,76 X 1,10 M. ACABADO: TINTILLA, SELLADOR (MÍNIMO 6 MANOS) Y LACA SEGÚN DISEÑO | H102: UND | I102: 4 | J102: 683832 | K102: =+ROUND(J102*I102,0) -> 2735328
D103: 016.044 | G103: MANTENIMIENTO Y RESTAURACION DE ANTEPECHOS Y DINTEL SUPERIOR EN MADERA PARA VENTANAS | H103: ML | I103: 160 | J103: 112337 | K103: =+ROUND(J103*I103,0) -> 17973920
D104: 016.045 | G104: SUMINISTRO, TRANSPORTE E INSTALACIÓN DE MADERA PARA ANTEPECHO INCLUYE DINTEL SUPERIOR EN MADERA PARA VENTANAS | H104: ML | I104: 46 | J104: 170442 | K104: =+ROUND(J104*I104,0) -> 7840332
D105: 016.017 | G105: SUMINISTRO, TRANSPORTE E INSTALACION DE MUEBLE BAJO MESON ANCHO: 0.60 M. CON FACHADA: MADECOR 19 MM. INTERIOR: MADECOR 15 MM. TIPO PIZANO O SIMILAR. ACABADO: SEGÚN PINTA SELECCIONADA DE CARTA COLORES MADECOR. (INCLUYE HOJAS PARA PUERTAS CON 2 RANURAS HORIZONTALES PINTADAS Y CON MARQUETE EN CANTO DECORATIVO. INTERIOR CON UN (1) ENTREPAÑO, TAPA SOBRE EL POYO DEL MUEBLE, HERRAJES, MANIJAS, SUMINISTRO DE TODOS LOS ACCESORIOS NECESARIOS PARA GARANTIZAR UNA CORRECTA INSTALACIÓN). | H105: M2 | I105: 4 | J105: 727257 | K105: =+ROUND(J105*I105,0) -> 2909028
C106: Subtotal | K106: =SUM(K100:K105) -> 33505044
D107: 017 | G107: CARPINTERIA METALICA
D108: 017.143 | G108: SUMINISTRO E INSTALACIÓN DE DIVISIÓN DE OFICINA EN PERFIL DE ALUMINIO DE 1"1/2 X 1"1/2 COLOR NATURAL REF.1101 CON VIDRIO DE SEGURIDAD LAMINADO INCOLORO 3+3 CON FRANJAS OPALIZADAS Y UNA PUERTA BATIENTE. | H108: M2 | I108: 191.435 | J108: 862042 | K108: =+ROUND(J108*I108,0) -> 165025010
D109: 017.144 | G109: SUMINISTRO E INSTALACIÓN DE DIVISIÓN DE OFICINA PLEGABLE CON VIDRIO DE SEGURIDAD TEMPLADO INCOLORO DE 8MM CON FRANJAS OPALIZADAS, ZÓCALO DE ALUMINIO EN LA PARTE INFERIOR Y SUPERIOR. | H109: M2 | I109: 25.56 | J109: 1342102 | K109: =+ROUND(J109*I109,0) -> 34304127
D110: 017.163 | G110: SUMINISTRO E INSTALACION DE VIDRIO FIJO REMATE A FACHADA, CON PERFIL DE 1"x1" CON ADAPATADOR REF 1101, CON PISAVIDRIO A PRESION, CON VIDRIO 3+3 (1,46*0,23) | H110: UND | I110: 17 | J110: 228238 | K110: =+ROUND(J110*I110,0) -> 3880046
C111: Subtotal | K111: =SUM(K108:K110) -> 203209183
D112: 019 | G112: PINTURA
D113: 019.001 | G113: SUMINISTRO, TRANSPORTE E INSTALACION ESTUCO Y VINILO 3 MANOS SOBRE MURO INTERIOR (INCLUYE ESTUCO, 1 MANO EN PINTURA TIPO 2 Y DOS MANOS EN PINTURA TIPO 1, FILOS Y DILATACIONES). COLOR SEGÚN DISEÑO POR M2 | H113: M2 | I113: 574.35 | J113: 40564 | K113: =+ROUND(J113*I113,0) -> 23297933
D114: 019.023 | G114: SUMINISTRO TRANSPORTE E INSTALACION ESTUCO Y 3 MANOS DE PINTURA ACRILTEX PARA BAÑO Y COCINA | H114: M2 | I114: 8 | J114: 47454 | K114: =+ROUND(J114*I114,0) -> 379632
C115: Subtotal | K115: =SUM(K113:K114) -> 23677565
D116: 022 | G116: ASEO GENERAL Y LIMPIEZA
D117: 022.001 | G117: ASEO GENERAL | H117: M2 | I117: 1194.14 | J117: 6269 | K117: =+ROUND(J117*I117,0) -> 7486064
C118: Subtotal | K118: =SUM(K117) -> 7486064
D119: 028 | G119: DESMONTES
D120: 028.005 | G120: DESMONTE APARATOS SANITARIOS | H120: UND | I120: 4 | J120: 104738 | K120: =+ROUND(J120*I120,0) -> 418952
D121: 028.008 | G121: DESMONTE CIELO RASO (INCLUYE RETIRO) | H121: M2 | I121: 794.14 | J121: 25951 | K121: =+ROUND(J121*I121,0) -> 20608727
D122: 028.012 | G122: DESMONTE PUERTAS (INCLUYE RETIRO) | H122: UND | I122: 42 | J122: 76142 | K122: =+ROUND(J122*I122,0) -> 3197964
D123: 028.085 | G123: DESMONTE DE DIVISIONES PISO TECHO O DE MEDIANA ALTURA CON PERFILERÍA METÁLICA O MADERA (INCLUYE RETIRO) | H123: M2 | I123: 552.681 | J123: 172688 | K123: =+ROUND(J123*I123,0) -> 95441377
D124: 028.087 | G124: DESMONTE LAMPARAS | H124: UND | I124: 392 | J124: 12290 | K124: =+ROUND(J124*I124,0) -> 4817680
D125: 028.088 | G125: DESMONTE PUNTOS ELECTRICOS INCLUYE APARATOS Y CABLE (NO INCLUYE RETIRO) | H125: UND | I125: 319 | J125: 22571 | K125: =+ROUND(J125*I125,0) -> 7200149
D126: 028.016 | G126: DESMONTE DE MUEBLE BAJO MESON | H126: ML | I126: 30.71 | J126: 36116 | K126: =+ROUND(J126*I126,0) -> 1109122
D127: 028.017 | G127: DESMONTE DE ESPEJO | H127: M2 | I127: 3.2 | J127: 8401 | K127: =+ROUND(J127*I127,0) -> 26883
D128: 028.100 | G128: DESMONTE PISOS FLOTANTE | H128: M2 | I128: 0 | J128: 19978 | K128: =+ROUND(J128*I128,0) -> 0
...

Sheet PROPUESTA ECONOMICA(Propone)
C4: Código | E4: Versión
C5: FORMULARIO 1
C6: PROPUESTA ECONÓMICA
C7: [La entidad puede utilizar este formulario de presentación de propuesta económica de forma detallada, sin perjuicio que la entidad pueda modificarlo o establecer la presentación de la oferta económica con un formulario distinto al indicado.] [Los proponentes emplearán el formulario establecido por la entidad para determinar su propuesta económica conforme al Formulario 1 - Presupuesto Oficial publicado por la Entidad]
C9: Cuando el proceso de contratación es estructurado por precios unitarios, la Entidad debe aplicar las notas 1, 2 y 3 del presente formato y las casillas de "Descripción", "Porcentaje" de la Administración, Utilidad y total A.I.U. resaltadas en color amarillo.
C11: Nº | D11: ÍTEM DE PAGO | E11: ESPECIFICACIONES | G11: DESCRIPCIÓN | H11: UND. | I11: CANTIDAD | J11: VALOR UNITARIO | K11: VALOR TOTAL
E12: GENERAL | F12: PARTICULAR
D13: 003 | G13: DESAGUES E INSTALACIONES SANITARIAS
D14: 003.014 | G14: SUMINISTRO, TRANSPORTE E INSTALACION PUNTO DESAGUE PVC 3" APARATOS SANITARIOS Y DESAGUES (INCLUYE CODO, YEE Y ACCESORIOS) | H14: UND. | I14: 1 | J14: =ROUND(PRESUPUESTO!J14*0.886,0) -> 139991 | K14: =+ROUND(J14*I14,0) -> 139991
D15: 003.015 | G15: SUMINISTRO, TRANSPORTE E INSTALACION PUNTO DESAGUE PVC 3" APARATOS SANITARIOS Y DESAGUES (INCLUYE CODO, YEE Y ACCESORIOS) | H15: UND. | I15: 1 | J15: =ROUND(PRESUPUESTO!J15*0.886,0) -> 182683 | K15: =+ROUND(J15*I15,0) -> 182683
C16: Subtotal | K16: =SUM(K14:K15) -> 322674
D17: 006 | G17: MAMPOSTERIA
D18: 006.019 | G18: SUMINISTRO, TRANSPORTE E INSTALACIÓN A TODO COSTO DE MURO EN SUPERBOARD 8 MM PINTADO Y TERMINADO (DOS CARAS). INCLUYE PERFILERÍA Y TODO LO NECESARIO PARA SU CORRECTA INSTALACIÓN | H18: M2 | I18: 135.19 | J18: =ROUND(PRESUPUESTO!J18*0.886,0) -> 178218 | K18: =+ROUND(J18*I18,0) -> 24093291
C19: Subtotal | K19: =SUM(K18) -> 24093291
D20: 007 | G20: INSTALACIONES HIDRAULICAS
D21: 007.017 | G21: SUMINISTRO, TRANSPORTE E INSTALACION PUNTO AGUA FRIA 1/2" PVC -P ( INCLUYE ACCESORIOS DE INSTALACIÓN ) | H21: UND | I21: 1 | J21: =ROUND(PRESUPUESTO!J21*0.886,0) -> 85091 | K21: =+ROUND(J21*I21,0) -> 85091
D22: 007.021 | G22: SUMINISTRO, TRANSPORTE E INSTALACION PUNTO AGUA CALIENTE 1/2" CPVC-P ( INCLUYE ACCESORIOS DE INSTALACIÓN ) | H22: UND | I22: 1 | J22: =ROUND(PRESUPUESTO!J22*0.886,0) -> 161688 | K22: =+ROUND(J22*I22,0) -> 161688
C23: Subtotal | K23: =SUM(K21:K22) -> 246779
D24: 08B | G24: INSTALACIONES HIDRAULICAS
G25: INSTALACIONES ELECTRICAS | J25: =ROUND(PRESUPUESTO!J25*0.886,0) -> 0
D26: 08B.844 | G26: SUMINISTRO E INSTALACIÓN BREAKER TOTALIZADOR 3X40A | H26: UND | I26: 3 | J26: =ROUND(PRESUPUESTO!J26*0.886,0) -> 522986 | K26: =+ROUND(J26*I26,0) -> 1568958
D27: 08B.845 | G27: SUMINISTRO E INSTALACIÓN DE ACOMETIDA A TR EN CABLE DE COBRE HFFRLS 3#8(F)+1#8(N)+1#8(T), POR BANDEJA EXISTENTE | H27: ML | I27: 150 | J27: =ROUND(PRESUPUESTO!J27*0.886,0) -> 68987 | K27: =+ROUND(J27*I27,0) -> 10348050
D28: 08B.846 | G28: SUMINISTRO E INSTALACIÓN TABLERO TRIFÁSICO DE 24 CTOS. CON ESPACIO PARA TOTALIZADOR (TN) | H28: UND | I28: 1 | J28: =ROUND(PRESUPUESTO!J28*0.886,0) -> 831914 | K28: =+ROUND(J28*I28,0) -> 831914
D29: 08B.847 | G29: SUMINISTRO E INSTALACIÓN BREAKER ENCHUFABLE 1X20 A | H29: UND | I29: 64 | J29: =ROUND(PRESUPUESTO!J29*0.886,0) -> 67268 | K29: =+ROUND(J29*I29,0) -> 4305152
D30: 08B.848 | G30: SUMINISTRO E INSTALACIÓN BREAKER ENCHUFABLE 2X20A | H30: UND | I30: 3 | J30: =ROUND(PRESUPUESTO!J30*0.886,0) -> 142125 | K30: =+ROUND(J30*I30,0) -> 426375
D31: 08B.849 | G31: SUMINISTRO E INSTALACIÓN SALIDA ALUMBRADO CON TUBERÍA PVC SCH40 Y CABLE #12 HFFRLS | H31: UND | I31: 238 | J31: =ROUND(PRESUPUESTO!J31*0.886,0) -> 156982 | K31: =+ROUND(J31*I31,0) -> 37361716
D32: 08B.850 | G32: SUMINISTRO E INSTALACIÓN SALIDA CON SENSOR DE MOVIMIENTO DE TECHO PARA ALUMBRADO CON TUBERÍA SCH40 Y CABLE #12 HFFRLS | H32: UND | I32: 5 | J32: =ROUND(PRESUPUESTO!J32*0.886,0) -> 222534 | K32: =+ROUND(J32*I32,0) -> 1112670
D33: 08B.851 | G33: SUMINISTRO E INSTALACIÓN SALIDA INTERRUPTOR SENCILLO CON TUBERÍA PVC SCH40 Y CABLE #12 HFFRLS | H33: UND | I33: 26 | J33: =ROUND(PRESUPUESTO!J33*0.886,0) -> 161969 | K33: =+ROUND(J33*I33,0) -> 4211194
D34: 08B.852 | G34: SUMINISTRO E INSTALACIÓN SALIDA INTERRUPTOR SENCILLO CON CABLE #12 LIBRE DE HALÓGENOS Y TUBERÍA PVC 1/2" | H34: UND | I34: 13 | J34: =ROUND(PRESUPUESTO!J34*0.886,0) -> 182387 | K34: =+ROUND(J34*I34,0) -> 2371031
D35: 08B.853 | G35: SUMINISTRO E INSTALACIÓN SALIDA INTERRUPTOR DOBLE CON TUBERÍA PVC SCH40 Y CABLE #12 HFFRLS | H35: UND | I35: 7 | J35: =ROUND(PRESUPUESTO!J35*0.886,0) -> 184108 | K35: =+ROUND(J35*I35,0) -> 1288756
D36: 08B.854 | G36: SUMINISTRO E INSTALACIÓN SALIDA INTERRUPTOR DOBLE CON CABLE #12 LIBRE DE HALÓGENOS Y TUBERÍA PVC 1/2" | H36: UND | I36: 3 | J36: =ROUND(PRESUPUESTO!J36*0.886,0) -> 201717 | K36: =+ROUND(J36*I36,0) -> 605151
D37: 08B.855 | G37: SUMINISTRO E INSTALACIÓN SALIDA INTERRUPTOR TRIPLE CON TUBERÍA PVC SCH40 Y CABLE #12 HFFRLS | H37: UND | I37: 2 | J37: =ROUND(PRESUPUESTO!J37*0.886,0) -> 207436 | K37: =+ROUND(J37*I37,0) -> 414872
... D61: 08B.880 | G61: SUMINISTRO E INSTALACIÓN TUBERÍA PVC SCH40 2" | H61: ML | I61: 59 | J61: =ROUND(PRESUPUESTO!J61*0.886,0) -> 21794 | K61: =+ROUND(J61*I61,0) -> 1285846
G62: INSTALACIONES VOZ-DATOS | J62: =ROUND(PRESUPUESTO!J62*0.886,0) -> 0
D63: 08B.881 | G63: SUMINISTRO E INSTALACIÓN CABLE UTP CAT. 6A 4P | H63: ML | I63: 9760 | J63: =ROUND(PRESUPUESTO!J63*0.886,0) -> 9856 | K63: =+ROUND(J63*I63,0) -> 96194560
D64: 08B.882 | G64: SUMINISTRO E INSTALACIÓN TOMA RJ45 DOBLE CAT. 6A | H64: UND | I64: 156 | J64: =ROUND(PRESUPUESTO!J64*0.886,0) -> 131772 | K64: =+ROUND(J64*I64,0) -> 20556432
D65: 08B.883 | G65: SUMINISTRO E INSTALACIÓN TOMA RJ45 SENCILLO CAT. 6A | H65: UND | I65: 10 | J65: =ROUND(PRESUPUESTO!J65*0.886,0) -> 79046 | K65: =+ROUND(J65*I65,0) -> 790460
D66: 08B.884 | G66: SUMINISTRO E INSTALACIÓN HERRAJE ANGULADO 48 PTOS | H66: UND | I66: 6 | J66: =ROUND(PRESUPUESTO!J66*0.886,0) -> 550717 | K66: =+ROUND(J66*I66,0) -> 3304302
D67: 08B.885 | G67: SUMINISTRO E INSTALACIÓN HERRAJE ANGULADO 24 PTOS | H67: UND | I67: 2 | J67: =ROUND(PRESUPUESTO!J67*0.886,0) -> 550717 | K67: =+ROUND(J67*I67,0) -> 1101434
D68: 08B.886 | G68: SUMINISTRO E INSTALACIÓN JACK RJ45 CAT. 6A (EN RACK) | H68: UND | I68: 322 | J68: =ROUND(PRESUPUESTO!J68*0.886,0) -> 54925 | K68: =+ROUND(J68*I68,0) -> 17685850
D69: 08B.887 | G69: SUMINISTRO E INSTALACIÓN PATCH CORD RJ45 30 CM CAT. 6A | H69: UND | I69: 322 | J69: =ROUND(PRESUPUESTO!J69*0.886,0) -> 33428 | K69: =+ROUND(J69*I69,0) -> 10763816
D70: 08B.888 | G70: SUMINISTRO E INSTALACIÓN ORGANIZADOR HORIZONTAL 2RU | H70: UND | I70: 6 | J70: =ROUND(PRESUPUESTO!J70*0.886,0) -> 449566 | K70: =+ROUND(J70*I70,0) -> 2697396
D71: 08B.889 | G71: CERTIFICACION SALIDA DATOS | H71: UND | I71: 322 | J71: =ROUND(PRESUPUESTO!J71*0.886,0) -> 22877 | K71: =+ROUND(J71*I71,0) -> 7366394
C72: Subtotal | K72: =SUM(K25:K71) -> 335357209
D73: 009 | G73: REVOQUES- RESANES
D74: 009.001 | G74: SUMINISTRO,TRANSPORTE E INSTALACION REVOQUE LISO MUROS 1:3 INTERIOR ( INCLUYE FILOS Y DILATACIONES ) | H74: M2 | I74: 4.8 | J74: =ROUND(PRESUPUESTO!J74*0.886,0) -> 44200 | K74: =+ROUND(J74*I74,0) -> 212160
C75: Subtotal | K75: =SUM(K74) -> 212160
D76: 011 | G76: CIELO RASOS
D77: 011.005 | G77: SUMINISTRO, TRANSPORTE E INSTALACION CIELO RASO SUSPENDIDO DRYWALL JUNTA PERDIDA DE 0-0,6M (PERFILERIA METÁLICA CL. 26. ESTRUCTURA CADA 40 CMS.) INCLUYE TRES (3) MANOS DE PINTURA | H77: M2 | I77: 530.3 | J77: =ROUND(PRESUPUESTO!J77*0.886,0) -> 110008 | K77: =+ROUND(J77*I77,0) -> 58337242
C78: Subtotal | K78: =SUM(K77) -> 58337242
D79: 012 | G79: PISOS - ACABADOS
D80: 012.098 | G80: SUMINISTRO, TRANSPORTE E INSTALACION ENCHAPE PISO BAÑO Petra Tortora 60x60cm Tipo CORONA o SIMILAR. Color Café/Marrón. (Incluye mortero de nivelación, boquilla y pegante) | H80: M2 | I80: 4 | J80: =ROUND(PRESUPUESTO!J80*0.886,0) -> 99409 | K80: =+ROUND(J80*I80,0) -> 397636
D81: 012.003 | G81: SUMINISTRO, TRANSPORTE E INSTALACION ALISTADO PISOS MORTERO 1:3 E= 0.04 MTS | H81: M2 | I81: 126.9 | J81: =ROUND(PRESUPUESTO!J81*0.886,0) -> 47964 | K81: =+ROUND(J81*I81,0) -> 6086632
D82: 012.105 | G82: SUMINISTRO, TRANSPORTE E INSTALACIÓN A TODO COSTO DE MORTERO AUTONIVELANTE HASTA 5,00MM DE ESPESOR PARA PISOS VINILICOS | H82: M2 | I82: 634.5 | J82: =ROUND(PRESUPUESTO!J82*0.886,0) -> 82724 | K82: =+ROUND(J82*I82,0) -> 52488378
D83: 012.006 | G83: SUMINISTRO, TRANSPORTE E INSTALACION CERAMICA PISO POMPEI TIPO ALFA O SIMILAR. COLOR CORAL O SHELL SEGÚN DISEÑO. INCLUYE MORTERO DE PEGA Y/O NIVELACIÓN | H83: M2 | I83: 5.03 | J83: =ROUND(PRESUPUESTO!J83*0.886,0) -> 92522 | K83: =+ROUND(J83*I83,0) -> 465386
D84: 012.088 | G84: SUMINISTRO E INSTALACION PISO HOMOGENEO VINILICO EN ROLLO, 2 MM DE ESPESOR, ANCHO ROLLO 2MT, COLOR SEGÚN DISEÑO, ALTO TRAFICO INCLUYE PREPARACION DE SUPERFICIE CON MASTICO, SOLDADURA PARA JUNTAS, ADHESIVO/PEGANTE, PARA AREAS | H84: M2 | I84: 634.5 | J84: =ROUND(PRESUPUESTO!J84*0.886,0) -> 259291 | K84: =+ROUND(J84*I84,0) -> 164520140
D85: 012.106 | G85: SUMINISTRO, TRANSPORTE E INSTALACION GUARDAESCOBA EN PVC RECUBIERTO | H85: ML | I85: 768.72 | J85: =ROUND(PRESUPUESTO!J85*0.886,0) -> 38125 | K85: =+ROUND(J85*I85,0) -> 29307450
D86: 012.077 | G86: SUMINISTRO, TRANSPORTE E INSTALACION BALDOSA GRANO TRADICIONAL PAYANDE TERRAZO. TIPO ALFA O SIMILAR. FONDO BLANCO (INCLUYE DESTRONCADA, PULIDA, BRILLADA, MORTERO DE NIVELACIÓN Y DILATACIÓN EN PVC.) | H86: M2 | I86: 4.53 | J86: =ROUND(PRESUPUESTO!J86*0.886,0) -> 240809 | K86: =+ROUND(J86*I86,0) -> 1090865
C87: Subtotal | K87: =SUM(K80:K86) -> 254356487
D88: 013 | G88: ENCHAPES Y ACCESORIOS
D89: 013.001 | G89: SUMINISTRO, TRANSPORTE E INSTALACION CERAMICA PARED POMPEI TIPO ALFA O SIMILAR. COLOR CORAL O SHELL SEGÚN DISEÑO (INCLUYE BOQUILLA COLOR Y WIN.) | H89: M2 | I89: 25.31 | J89: =ROUND(PRESUPUESTO!J89*0.886,0) -> 104516 | K89: =+ROUND(J89*I89,0) -> 2645300
D90: 013.065 | G90: SUMINISTRO, TRANSPORTE E INSTALACION MESON EN QUARZTONE BLANCO POLAR 1,00X0,50M | H90: ML | I90: 3 | J90: =ROUND(PRESUPUESTO!J90*0.886,0) -> 737101 | K90: =+ROUND(J90*I90,0) -> 2211303
C91: Subtotal | K91: =SUM(K89:K90) -> 4856603
D92: 014 | G92: VIDRIOS Y ESPEJOS
D93: 014.001 | G93: SUMINISTRO, TRANSPORTE E INSTALACION ESPEJO 4 MM. FLOTADO BISELADO Y SIN MARCO. (INCLUYE LOS ELEMENTOS DE FIJACIÓN AL MURO). | H93: M2 | I93: 1.02 | J93: =ROUND(PRESUPUESTO!J93*0.886,0) -> 213827 | K93: =+ROUND(J93*I93,0) -> 218104
C94: Subtotal | K94: =SUM(K93) -> 218104
D95: 015 | G95: APARATOS SANITARIOS
D96: 015.004 | G96: SUMINISTRO, TRANSPORTE E INSTALACION SANITARIO MONTECARLO ELONGADO BLANCO CORONA O SIMILAR. (CONJUNTO SANITARIO QUE INCLUYE SANITARIO, TAPA, ACCESORIOS DE CONEXIÓN E INSTALACIÓN.) | H96: UND | I96: 2 | J96: =ROUND(PRESUPUESTO!J96*0.886,0) -> 1073363 | K96: =+ROUND(J96*I96,0) -> 2146726
D97: 015.012 | G97: SUMINISTRO, TRANSPORTE E INSTALACION LAVAMANOS SOBREPONER LINEA STILO COLOR BLANCO TIPO CORONA REF. 072591001 O SIMILAR (INCLUYE CONJUNTO GRIFERIA DESAGÜE AUTOMATICO, SIFÓN BOTELLA, ACOPLE). | H97: UND | I97: 2 | J97: =ROUND(PRESUPUESTO!J97*0.886,0) -> 704277 | K97: =+ROUND(J97*I97,0) -> 1408554
C98: Subtotal | K98: =SUM(K96:K97) -> 3555280
D99: 016 | G99: CARPINTERIA DE MADERA
D100: 016.007 | G100: SUMINISTRO, TRANSPORTE E INSTALACION PUERTA ENTAMBORADA EN MADEFONDO - TIPO PIZANO ARQUITECTÓNICA O SIMILAR. ANCHO: 0,51 A 0,75 M. ALTO: 1,80 A 2,40 M. HOJA LISA CON 4 RANURAS HORIZONTALES PINTADAS Y CON MARQUETE EN CANTO DECORATIVO. ACABADO: SEGÚN PINTA SELECCIONADA DE CARTA COLORES MADECOR. (INCLUYE BISAGRAS). | H100: UND | I100: 2 | J100: =ROUND(PRESUPUESTO!J100*0.886,0) -> 419696 | K100: =+ROUND(J100*I100,0) -> 839392
D101: 016.008 | G101: SUMINISTRO, TRANSPORTE E INSTALACION PUERTA ENTAMBORADA EN MADEFONDO - TIPO PIZANO ARQUITECÓNICA O SIMILAR. ANCHO: 0,76 A 1,10 M. ALTO: 1,80 A 2,40 M. HOJA LISA CON 4 RANURAS HORIZONTALES PINTADAS Y CON MARQUETE EN CANTO DECORATIVO. ACABADO: SEGÚN PINTA SELECCIONADA DE CARTA COLORES MADECOR. (INCLUYE BISAGRAS). | H101: UND | I101: 2 | J101: =ROUND(PRESUPUESTO!J101*0.886,0) -> 486876 | K101: =+ROUND(J101*I101,0) -> 973752
D102: 016.010 | G102: SUMINISTRO, TRANSPORTE E INSTALACION MARCO EN TABLEX ENCHAPADO OKUME - KIT DE MARKO CLASSICO TIPO PIZANO O SIMILAR. (2 LARGUEROS DE 2,40 M Y UN CABEZAL DE 1,20 M.) ANCHO MURO: 10 A 18 CM ANCHO PUERTA: 0,76 X 1,10 M. ACABADO: TINTILLA, SELLADOR (MÍNIMO 6 MANOS) Y LACA SEGÚN DISEÑO | H102: UND | I102: 4 | J102: =ROUND(PRESUPUESTO!J102*0.886,0) -> 605875 | K102: =+ROUND(J102*I102,0) -> 2423500
D103: 016.044 | G103: MANTENIMIENTO Y RESTAURACION DE ANTEPECHOS Y DINTEL SUPERIOR EN MADERA PARA VENTANAS | H103: ML | I103: 160 | J103: =ROUND(PRESUPUESTO!J103*0.886,0) -> 99531 | K103: =+ROUND(J103*I103,0) -> 15924960
D104: 016.045 | G104: SUMINISTRO, TRANSPORTE E INSTALACIÓN DE MADERA PARA ANTEPECHO INCLUYE DINTEL SUPERIOR EN MADERA PARA VENTANAS | H104: ML | I104: 46 | J104: =ROUND(PRESUPUESTO!J104*0.886,0) -> 151012 | K104: =+ROUND(J104*I104,0) -> 6946552
D105: 016.017 | G105: SUMINISTRO, TRANSPORTE E INSTALACION DE MUEBLE BAJO MESON ANCHO: 0.60 M. CON FACHADA: MADECOR 19 MM. INTERIOR: MADECOR 15 MM. TIPO PIZANO O SIMILAR. ACABADO: SEGÚN PINTA SELECCIONADA DE CARTA COLORES MADECOR. (INCLUYE HOJAS PARA PUERTAS CON 2 RANURAS HORIZONTALES PINTADAS Y CON MARQUETE EN CANTO DECORATIVO. INTERIOR CON UN (1) ENTREPAÑO, TAPA SOBRE EL POYO DEL MUEBLE, HERRAJES, MANIJAS, SUMINISTRO DE TODOS LOS ACCESORIOS NECESARIOS PARA GARANTIZAR UNA CORRECTA INSTALACIÓN). | H105: M2 | I105: 4 | J105: =ROUND(PRESUPUESTO!J105*0.886,0) -> 644350 | K105: =+ROUND(J105*I105,0) -> 2577400
C106: Subtotal | K106: =SUM(K100:K105) -> 29685556
D107: 017 | G107: CARPINTERIA METALICA
D108: 017.143 | G108: SUMINISTRO E INSTALACIÓN DE DIVISIÓN DE OFICINA EN PERFIL DE ALUMINIO DE 1"1/2 X 1"1/2 COLOR NATURAL REF.1101 CON VIDRIO DE SEGURIDAD LAMINADO INCOLORO 3+3 CON FRANJAS OPALIZADAS Y UNA PUERTA BATIENTE. | H108: M2 | I108: 191.435 | J108: =ROUND(PRESUPUESTO!J108*0.886,0) -> 763769 | K108: =+ROUND(J108*I108,0) -> 146212119
D109: 017.144 | G109: SUMINISTRO E INSTALACIÓN DE DIVISIÓN DE OFICINA PLEGABLE CON VIDRIO DE SEGURIDAD TEMPLADO INCOLORO DE 8MM CON FRANJAS OPALIZADAS, ZÓCALO DE ALUMINIO EN LA PARTE INFERIOR Y SUPERIOR. | H109: M2 | I109: 25.56 | J109: =ROUND(PRESUPUESTO!J109*0.886,0) -> 1189102 | K109: =+ROUND(J109*I109,0) -> 30393447
D110: 017.163 | G110: SUMINISTRO E INSTALACION DE VIDRIO FIJO REMATE A FACHADA, CON PERFIL DE 1"x1" CON ADAPATADOR REF 1101, CON PISAVIDRIO A PRESION, CON VIDRIO 3+3 (1,46*0,23) | H110: UND | I110: 17 | J110: =ROUND(PRESUPUESTO!J110*0.886,0) -> 202219 | K110: =+ROUND(J110*I110,0) -> 3437723
C111: Subtotal | K111: =SUM(K108:K110) -> 180043289
D112: 019 | G112: PINTURA
D113: 019.001 | G113: SUMINISTRO, TRANSPORTE E INSTALACION ESTUCO Y VINILO 3 MANOS SOBRE MURO INTERIOR (INCLUYE ESTUCO, 1 MANO EN PINTURA TIPO 2 Y DOS MANOS EN PINTURA TIPO 1, FILOS Y DILATACIONES). COLOR SEGÚN DISEÑO POR M2 | H113: M2 | I113: 574.35 | J113: =ROUND(PRESUPUESTO!J113*0.886,0) -> 35940 | K113: =+ROUND(J113*I113,0) -> 20642139
D114: 019.023 | G114: SUMINISTRO TRANSPORTE E INSTALACION ESTUCO Y 3 MANOS DE PINTURA ACRILTEX PARA BAÑO Y COCINA | H114: M2 | I114: 8 | J114: =ROUND(PRESUPUESTO!J114*0.886,0) -> 42044 | K114: =+ROUND(J114*I114,0) -> 336352
C115: Subtotal | K115: =SUM(K113:K114) -> 20978491
D116: 022 | G116: ASEO GENERAL Y LIMPIEZA
D117: 022.001 | G117: ASEO GENERAL | H117: M2 | I117: 1194.14 | J117: =ROUND(PRESUPUESTO!J117*0.886,0) -> 5554 | K117: =+ROUND(J117*I117,0) -> 6632254
C118: Subtotal | K118: =SUM(K117) -> 6632254
D119: 028 | G119: DESMONTES
D120: 028.005 | G120: DESMONTE APARATOS SANITARIOS | H120: UND | I120: 4 | J120: =ROUND(PRESUPUESTO!J120*0.886,0) -> 92798 | K120: =+ROUND(J120*I120,0) -> 371192
D121: 028.008 | G121: DESMONTE CIELO RASO (INCLUYE RETIRO) | H121: M2 | I121: 794.14 | J121: =ROUND(PRESUPUESTO!J121*0.886,0) -> 22993 | K121: =+ROUND(J121*I121,0) -> 18259661
D122: 028.012 | G122: DESMONTE PUERTAS (INCLUYE RETIRO) | H122: UND | I122: 42 | J122: =ROUND(PRESUPUESTO!J122*0.886,0) -> 67462 | K122: =+ROUND(J122*I122,0) -> 2833404
D123: 028.085 | G123: DESMONTE DE DIVISIONES PISO TECHO O DE MEDIANA ALTURA CON PERFILERÍA METÁLICA O MADERA (INCLUYE RETIRO) | H123: M2 | I123: 552.681 | J123: =ROUND(PRESUPUESTO!J123*0.886,0) -> 153002 | K123: =+ROUND(J123*I123,0) -> 84561298
D124: 028.087 | G124: DESMONTE LAMPARAS | H124: UND | I124: 392 | J124: =ROUND(PRESUPUESTO!J124*0.886,0) -> 10889 | K124: =+ROUND(J124*I124,0) -> 4268488
D125: 028.088 | G125: DESMONTE PUNTOS ELECTRICOS INCLUYE APARATOS Y CABLE (NO INCLUYE RETIRO) | H125: UND | I125: 319 | J125: =ROUND(PRESUPUESTO!J125*0.886,0) -> 19998 | K125: =+ROUND(J125*I125,0) -> 6379362
D126: 028.016 | G126: DESMONTE DE MUEBLE BAJO MESON | H126: ML | I126: 30.71 | J126: =ROUND(PRESUPUESTO!J126*0.886,0) -> 31999 | K126: =+ROUND(J126*I126,0) -> 982689
D127: 028.017 | G127: DESMONTE DE ESPEJO | H127: M2 | I127: 3.2 | J127: =ROUND(PRESUPUESTO!J127*0.886,0) -> 7443 | K127: =+ROUND(J127*I127,0) -> 23818
D128: 028.100 | G128: DESMONTE PISOS FLOTANTE | H128: M2 | I128: 0 | J128: =ROUND(PRESUPUESTO!J128*0.886,0) -> 17701 | K128: =+ROUND(J128*I128,0) -> 0
...
